{
  "version": "6.3.0",
  "flags": {},
  "shapes": [
    {
      "label": "phone",
      "points": [
        [
          567.3109243697478,
          122.18487394957982
        ],
        [
          699.2436974789915,
          124.70588235294117
        ],
        [
          715.2100840336134,
          136.47058823529412
        ],
        [
          723.6134453781511,
          164.2016806722689
        ],
        [
          730.3361344537815,
          354.11764705882354
        ],
        [
          650.5042016806722,
          364.20168067226894
        ],
        [
          644.6218487394957,
          380.16806722689074
        ],
        [
          716.0504201680671,
          407.89915966386553
        ],
        [
          726.1344537815125,
          498.65546218487395
        ],
        [
          705.9663865546217,
          507.89915966386553
        ],
        [
          571.5126050420167,
          506.218487394958
        ],
        [
          555.5462184873949,
          494.4537815126051
        ],
        [
          539.579831932773,
          492.7731092436975
        ],
        [
          534.5378151260503,
          438.9915966386555
        ],
        [
          535.3781512605042,
          204.53781512605042
        ],
        [
          541.2605042016806,
          133.94957983193277
        ]
      ],
      "group_id": null,
      "description": "",
      "shape_type": "polygon",
      "flags": {},
      "mask": null
    }
  ],
  "imagePath": "frame_389.jpg",
  "imageData": null,
  "imageHeight": 720,
  "imageWidth": 1280
}