{
  "version": "6.3.0",
  "flags": {},
  "shapes": [
    {
      "label": "phone",
      "points": [
        [
          729.4957983193277,
          47.39495798319326
        ],
        [
          896.7226890756302,
          115.46218487394957
        ],
        [
          909.3277310924369,
          142.35294117647058
        ],
        [
          854.7058823529411,
          271.7647058823529
        ],
        [
          832.8571428571428,
          273.4453781512605
        ],
        [
          811.8487394957982,
          300.33613445378154
        ],
        [
          818.5714285714286,
          342.3529411764706
        ],
        [
          806.8067226890755,
          372.60504201680675
        ],
        [
          734.5378151260503,
          421.34453781512605
        ],
        [
          681.5966386554621,
          510.4201680672269
        ],
        [
          678.235294117647,
          527.2268907563025
        ],
        [
          530.3361344537815,
          464.20168067226894
        ],
        [
          511.00840336134445,
          435.6302521008403
        ],
        [
          558.90756302521,
          315.4621848739496
        ],
        [
          674.0336134453781,
          70.92436974789915
        ]
      ],
      "group_id": null,
      "description": "",
      "shape_type": "polygon",
      "flags": {},
      "mask": null
    }
  ],
  "imagePath": "frame_62.jpg",
  "imageData": null,
  "imageHeight": 720,
  "imageWidth": 1280
}