{
  "version": "6.3.0",
  "flags": {},
  "shapes": [
    {
      "label": "phone",
      "points": [
        [
          414.36974789915956,
          485.21008403361344
        ],
        [
          396.72268907563017,
          475.96638655462186
        ],
        [
          394.2016806722688,
          453.2773109243698
        ],
        [
          400.9243697478991,
          430.5882352941177
        ],
        [
          411.00840336134445,
          428.06722689075633
        ],
        [
          490.84033613445365,
          487.7310924369748
        ],
        [
          494.2016806722688,
          502.8571428571429
        ],
        [
          511.00840336134445,
          500.33613445378154
        ],
        [
          568.9915966386554,
          533.9495798319327
        ],
        [
          572.3529411764705,
          577.6470588235294
        ],
        [
          558.0672268907563,
          556.6386554621849
        ],
        [
          541.2605042016806,
          533.109243697479
        ],
        [
          517.7310924369747,
          515.4621848739496
        ],
        [
          497.563025210084,
          512.9411764705883
        ],
        [
          468.1512605042016,
          496.97478991596637
        ],
        [
          450.50420168067217,
          484.3697478991597
        ],
        [
          426.13445378151255,
          484.3697478991597
        ]
      ],
      "group_id": null,
      "description": "",
      "shape_type": "polygon",
      "flags": {},
      "mask": null
    }
  ],
  "imagePath": "frame_464.jpg",
  "imageData": null,
  "imageHeight": 720,
  "imageWidth": 1280
}