{
  "version": "6.3.0",
  "flags": {},
  "shapes": [
    {
      "label": "phone",
      "points": [
        [
          26.11111111111105,
          715.5555555555555
        ],
        [
          214.99999999999994,
          472.5
        ],
        [
          252.49999999999994,
          458.6111111111111
        ],
        [
          281.66666666666663,
          421.1111111111111
        ],
        [
          281.66666666666663,
          380.83333333333337
        ],
        [
          435.8333333333333,
          176.66666666666663
        ],
        [
          477.49999999999994,
          165.55555555555554
        ],
        [
          721.9444444444445,
          297.5
        ],
        [
          755.2777777777777,
          332.2222222222222
        ],
        [
          751.1111111111111,
          382.2222222222222
        ],
        [
          646.9444444444445,
          551.6666666666666
        ],
        [
          642.7777777777777,
          537.7777777777778
        ],
        [
          595.5555555555555,
          555.8333333333334
        ],
        [
          553.8888888888888,
          666.9444444444445
        ],
        [
          505.2777777777777,
          718.3333333333334
        ],
        [
          501.38888888888886,
          720.0
        ],
        [
          335.83333333333326,
          720.0
        ]
      ],
      "group_id": null,
      "description": "",
      "shape_type": "polygon",
      "flags": {},
      "mask": null
    }
  ],
  "imagePath": "frame_697.jpg",
  "imageData": null,
  "imageHeight": 720,
  "imageWidth": 1280
}