{
  "version": "6.3.0",
  "flags": {},
  "shapes": [
    {
      "label": "phone",
      "points": [
        [
          569.8319327731092,
          468.4033613445378
        ],
        [
          870.672268907563,
          67.56302521008402
        ],
        [
          911.0084033613444,
          61.68067226890754
        ],
        [
          1116.8907563025211,
          172.60504201680672
        ],
        [
          1128.655462184874,
          196.1344537815126
        ],
        [
          1126.9747899159665,
          231.42857142857142
        ],
        [
          1094.201680672269,
          292.7731092436975
        ],
        [
          770.672268907563,
          717.983193277311
        ],
        [
          765.6302521008403,
          717.983193277311
        ],
        [
          516.8907563025209,
          718.8235294117648
        ],
        [
          458.0672268907562,
          665.8823529411765
        ],
        [
          456.3865546218487,
          623.8655462184875
        ],
        [
          513.5294117647059,
          547.3949579831933
        ],
        [
          558.90756302521,
          561.6806722689075
        ],
        [
          600.0840336134453,
          540.6722689075631
        ]
      ],
      "group_id": null,
      "description": "",
      "shape_type": "polygon",
      "flags": {},
      "mask": null
    }
  ],
  "imagePath": "frame_435.jpg",
  "imageData": null,
  "imageHeight": 720,
  "imageWidth": 1280
}